{
  "service_id": "discord",
  "doc_type": "privacy_policy",
  "name": "Discord Privacy Policy",
  "generated_at": "2026-02-20T02:36:39+00:00",
  "mode_requested": "semantic",
  "mode_used": "semantic",
  "provenance": {
    "old": {
      "fetched_at": "2026-02-10T02:53:25+00:00",
      "content_sha256": "892310f8c574b709dec02027841d7d9ce45406956a3dd6e600d1e28353d2a167",
      "source": {
        "type": "ota",
        "repo": "OpenTermsArchive/france-versions",
        "branch": "main",
        "path": "Discord/Privacy Policy.md",
        "url": "https://raw.githubusercontent.com/OpenTermsArchive/france-versions/main/Discord/Privacy Policy.md"
      }
    },
    "new": {
      "fetched_at": "2026-02-20T02:36:33+00:00",
      "content_sha256": "703d29604ed391b757f178cb046d490b023872cc5625bb1e6404efdf9f15d489",
      "source": {
        "type": "ota",
        "repo": "OpenTermsArchive/france-versions",
        "branch": "main",
        "path": "Discord/Privacy Policy.md",
        "url": "https://raw.githubusercontent.com/OpenTermsArchive/france-versions/main/Discord/Privacy Policy.md"
      }
    }
  },
  "engine": {
    "mode": "semantic",
    "model_name": "all-MiniLM-L6-v2",
    "num_changes": 1
  },
  "changes": [
    {
      "category": "Other policy change",
      "type": "removed",
      "risk_score": 0.5,
      "similarity": 0.4548022150993347,
      "old_index": 48,
      "new_index": null,
      "old": "‍ With your consent",
      "new": null,
      "explanation": "This section of the policy text has been modified.",
      "suggested_action": "Read this part of the policy carefully to understand how it affects your data."
    }
  ]
}